[
  {
    "id": "belt_alpide",
    "type": "mountain",
    "name": "Alpide Belt",
    "geometryType": "line",
    "geometry": {
      "type": "LineString",
      "coordinates": [
        [
          -10,
          36
        ],
        [
          10,
          40
        ],
        [
          35,
          38
        ],
        [
          60,
          35
        ],
        [
          80,
          30
        ],
        [
          95,
          28
        ],
        [
          105,
          20
        ]
      ]
    },
    "labelPoint": [
      45,
      36
    ],
    "packIds": [
      "world_tectonic_plates_volcano_belts"
    ],
    "bbox": [
      -10,
      20,
      105,
      40
    ]
  },
  {
    "id": "belt_ring_of_fire",
    "type": "mountain",
    "name": "Ring of Fire",
    "geometryType": "line",
    "geometry": {
      "type": "LineString",
      "coordinates": [
        [
          -78,
          -55
        ],
        [
          -75,
          -20
        ],
        [
          -100,
          20
        ],
        [
          -125,
          45
        ],
        [
          -150,
          60
        ],
        [
          -170,
          55
        ],
        [
          160,
          50
        ],
        [
          140,
          35
        ],
        [
          130,
          20
        ],
        [
          120,
          10
        ],
        [
          105,
          -5
        ],
        [
          120,
          -35
        ],
        [
          160,
          -45
        ]
      ]
    },
    "labelPoint": [
      -140,
      10
    ],
    "packIds": [
      "world_tectonic_plates_volcano_belts"
    ],
    "bbox": [
      -170,
      -55,
      160,
      60
    ]
  },
  {
    "id": "plate_african",
    "type": "region",
    "name": "African Plate",
    "geometryType": "polygon",
    "geometry": {
      "type": "Polygon",
      "coordinates": [
        [
          [
            -20,
            -40
          ],
          [
            55,
            -40
          ],
          [
            55,
            35
          ],
          [
            -20,
            35
          ],
          [
            -20,
            -40
          ]
        ]
      ]
    },
    "labelPoint": [
      20,
      0
    ],
    "packIds": [
      "world_tectonic_plates_volcano_belts"
    ],
    "bbox": [
      -20,
      -40,
      55,
      35
    ]
  },
  {
    "id": "plate_eurasian",
    "type": "region",
    "name": "Eurasian Plate",
    "geometryType": "polygon",
    "geometry": {
      "type": "Polygon",
      "coordinates": [
        [
          [
            -10,
            15
          ],
          [
            170,
            15
          ],
          [
            170,
            80
          ],
          [
            -10,
            80
          ],
          [
            -10,
            15
          ]
        ]
      ]
    },
    "labelPoint": [
      80,
      50
    ],
    "packIds": [
      "world_tectonic_plates_volcano_belts"
    ],
    "bbox": [
      -10,
      15,
      170,
      80
    ]
  },
  {
    "id": "plate_north_american",
    "type": "region",
    "name": "North American Plate",
    "geometryType": "polygon",
    "geometry": {
      "type": "Polygon",
      "coordinates": [
        [
          [
            -170,
            10
          ],
          [
            -50,
            10
          ],
          [
            -50,
            80
          ],
          [
            -170,
            80
          ],
          [
            -170,
            10
          ]
        ]
      ]
    },
    "labelPoint": [
      -110,
      50
    ],
    "packIds": [
      "world_tectonic_plates_volcano_belts"
    ],
    "bbox": [
      -170,
      10,
      -50,
      80
    ]
  },
  {
    "id": "plate_pacific",
    "type": "region",
    "name": "Pacific Plate",
    "geometryType": "polygon",
    "geometry": {
      "type": "Polygon",
      "coordinates": [
        [
          [
            -170,
            -55
          ],
          [
            -100,
            -55
          ],
          [
            -100,
            55
          ],
          [
            -170,
            55
          ],
          [
            -170,
            -55
          ]
        ]
      ]
    },
    "labelPoint": [
      -135,
      0
    ],
    "packIds": [
      "world_tectonic_plates_volcano_belts"
    ],
    "bbox": [
      -170,
      -55,
      -100,
      55
    ]
  },
  {
    "id": "plate_south_american",
    "type": "region",
    "name": "South American Plate",
    "geometryType": "polygon",
    "geometry": {
      "type": "Polygon",
      "coordinates": [
        [
          [
            -90,
            -60
          ],
          [
            -20,
            -60
          ],
          [
            -20,
            20
          ],
          [
            -90,
            20
          ],
          [
            -90,
            -60
          ]
        ]
      ]
    },
    "labelPoint": [
      -60,
      -20
    ],
    "packIds": [
      "world_tectonic_plates_volcano_belts"
    ],
    "bbox": [
      -90,
      -60,
      -20,
      20
    ]
  }
]
