{
  "basin_mississippi": {
    "type": "Polygon",
    "coordinates": [
      [
        [
          -108,
          28
        ],
        [
          -80,
          28
        ],
        [
          -80,
          49
        ],
        [
          -108,
          49
        ],
        [
          -108,
          28
        ]
      ]
    ]
  },
  "biome_taiga": {
    "type": "Polygon",
    "coordinates": [
      [
        [
          30,
          52
        ],
        [
          120,
          52
        ],
        [
          120,
          68
        ],
        [
          30,
          68
        ],
        [
          30,
          52
        ]
      ]
    ]
  },
  "current_gulf_stream": {
    "type": "LineString",
    "coordinates": [
      [
        -80,
        25
      ],
      [
        -70,
        35
      ],
      [
        -55,
        45
      ],
      [
        -20,
        55
      ]
    ]
  },
  "eez_australia": {
    "type": "Polygon",
    "coordinates": [
      [
        [
          105,
          -46
        ],
        [
          165,
          -46
        ],
        [
          165,
          -8
        ],
        [
          105,
          -8
        ],
        [
          105,
          -46
        ]
      ]
    ]
  },
  "india_range_vindhya": {
    "type": "Polygon",
    "coordinates": [
      [
        [
          76.87867299999994,
          22.713568
        ],
        [
          75.91199800000004,
          22.223334
        ],
        [
          75.74720300000001,
          22.203742
        ],
        [
          75.39808199999993,
          22.253791
        ],
        [
          75.28711999999996,
          22.253485
        ],
        [
          73.90040099999999,
          21.845893
        ],
        [
          73.774181,
          21.850348
        ],
        [
          73.71693000000005,
          21.867499
        ],
        [
          73.64490799999999,
          21.925544
        ],
        [
          73.58924400000001,
          22.023017
        ],
        [
          73.55176800000004,
          22.146186
        ],
        [
          73.53394600000001,
          22.281684
        ],
        [
          73.53724199999999,
          22.415961
        ],
        [
          73.56348700000001,
          22.535407
        ],
        [
          73.61402399999997,
          22.626593
        ],
        [
          73.69068400000003,
          22.676032
        ],
        [
          73.717174,
          22.70246
        ],
        [
          73.823985,
          22.716864
        ],
        [
          74.40821400000004,
          22.640998
        ],
        [
          74.51624600000002,
          22.656501
        ],
        [
          74.615001,
          22.702216
        ],
        [
          74.63038200000005,
          22.715155
        ],
        [
          74.71583099999998,
          22.82331
        ],
        [
          74.774181,
          22.861335
        ],
        [
          76.07960000000003,
          23.192267
        ],
        [
          78.39905799999997,
          24.488593
        ],
        [
          78.64478600000007,
          24.537116
        ],
        [
          78.95130500000005,
          24.540595
        ],
        [
          79.25245199999995,
          24.476264
        ],
        [
          79.38855999999998,
          24.412909
        ],
        [
          79.508556,
          24.325568
        ],
        [
          79.60718799999995,
          24.21192
        ],
        [
          79.66688099999999,
          24.081244
        ],
        [
          79.68397099999993,
          23.937995
        ],
        [
          79.663951,
          23.790107
        ],
        [
          79.61207100000001,
          23.645453
        ],
        [
          79.53370199999995,
          23.51203
        ],
        [
          79.43372599999998,
          23.397773
        ],
        [
          79.31776000000002,
          23.310553
        ],
        [
          79.19105100000002,
          23.258246
        ],
        [
          78.29029400000002,
          23.20423
        ],
        [
          78.24097699999993,
          23.181403
        ],
        [
          78.19837499999994,
          23.15174
        ],
        [
          78.04395599999998,
          23.000556
        ],
        [
          77.92969800000003,
          22.921759
        ],
        [
          77.78907300000003,
          22.857184
        ],
        [
          76.87867299999994,
          22.713568
        ]
      ]
    ]
  },
  "strait_bosporus": {
    "type": "LineString",
    "coordinates": [
      [
        28.96,
        41.25
      ],
      [
        29.12,
        41
      ]
    ]
  }
}
